Metadata-Version: 2.1
Name: prisma-sh
Version: 0.0.1b1
Summary: `Command-line access to the controller-based Prisma SD-WAN ION Troubleshooting Toolkit.`
Home-page: https://github.com/ebob9/prisma-sh
Author: Aaron Edwards
Author-email: prisma-sh@ebob9.com
License: MIT
Classifier: Development Status :: 4 - Beta
Classifier: Intended Audience :: End Users/Desktop
Classifier: License :: OSI Approved :: MIT License
Classifier: Programming Language :: Python :: 3.10
Requires-Python: >=3.10.1
License-File: LICENSE
